lcdp_flask_utils/__init__.py
lcdp_flask_utils/app.py
lcdp_flask_utils/datadog.py
lcdp_flask_utils-1.5.9.dist-info/METADATA
lcdp_flask_utils-1.5.9.dist-info/WHEEL
lcdp_flask_utils-1.5.9.dist-info/RECORD
